# TIL - 2023.12.04 (월)
## 자바 Constant

자바 컴파일러가 클래스 코드를 컴파일하면 자바 바이트 코드 (`.class`) 를 생성한다.
- JVM은 클래스 파일이 실행될 때 위치를 찾아 메모리에 로딩한다
- 로딩 과정에서 **클래스 파일을 파싱**하고 파싱된 데이터를 **JVM의 메소드 영역**에 위치시킨다
- 메소드 영역은 스레드 간에 공유되는 메모리 공간이다

**Constant Pool**

상수 풀은 클래스 파일의 중요한 부분 중 하나로, 클래스 내에서 **심볼 테이블** 역할을 한다.
- 클래스 내에서 **참조되는 클래스들의 이름**을 포함한다
- 문자열과 숫자 **상수의 초기 값**을 저장한다

예를 들어, 다음과 같은 코드를 실행하보자.
```java
class Hello {

    public static void main(String[] args) {
        for (int i = 0; i < 10; i++) {
            System.out.println("Hello from Hello.main!");
        }
    }
}
```

이를 JDK에서 제공하는 클래스 파일 `disassembler`로 실행하면 클래스 파일에 대한 정보를 얻을 수 있다.
그중에서 상수 풀에 관한 내용은 아래와 같았다.
```
Constant pool:
   #1 = Methodref          #2.#3          // java/lang/Object."<init>":()V
   #2 = Class              #4             // java/lang/Object
   #3 = NameAndType        #5:#6          // "<init>":()V
   #4 = Utf8               java/lang/Object
   #5 = Utf8               <init>
   #6 = Utf8               ()V
   #7 = Fieldref           #8.#9          // java/lang/System.out:Ljava/io/PrintStream;
   #8 = Class              #10            // java/lang/System
   #9 = NameAndType        #11:#12        // out:Ljava/io/PrintStream;
  #10 = Utf8               java/lang/System
  #11 = Utf8               out
  #12 = Utf8               Ljava/io/PrintStream;
  #13 = String             #14            // Hello from Hello.main!
  #14 = Utf8               Hello from Hello.main!
  #15 = Methodref          #16.#17        // java/io/PrintStream.println:(Ljava/lang/String;)V
  #16 = Class              #18            // java/io/PrintStream
  #17 = NameAndType        #19:#20        // println:(Ljava/lang/String;)V
  #18 = Utf8               java/io/PrintStream
  #19 = Utf8               println
  #20 = Utf8               (Ljava/lang/String;)V
  #21 = Class              #22            // learn/java/testrepository/plain/loader/Hello
  #22 = Utf8               learn/java/testrepository/plain/loader/Hello
  #23 = Utf8               Code
  #24 = Utf8               LineNumberTable
  #25 = Utf8               LocalVariableTable
  #26 = Utf8               this
  #27 = Utf8               Llearn/java/testrepository/plain/loader/Hello;
  #28 = Utf8               main
  #29 = Utf8               ([Ljava/lang/String;)V
  #30 = Utf8               i
  #31 = Utf8               I
  #32 = Utf8               args
  #33 = Utf8               [Ljava/lang/String;
  #34 = Utf8               StackMapTable
  #35 = Utf8               MethodParameters
  #36 = Utf8               SourceFile
  #37 = Utf8               Hello.java

```
- 왼쪽에 기입된 숫자는 엔트리 번호이다
- 두 번째 칼럼 값은 엔트리의 타입이다
- 세 번째 칼럼 값은 엔트리의 값이다

**Class 타입**

```
#21 = Class              #22            // learn/java/testrepository/plain/loader/Hello
#22 = Utf8               learn/java/testrepository/plain/loader/Hello
```
- `Utf8`은 자바 클래스 파일에서 **문자열 포맷**을 나타내기 위한 타입이다
- 상수 풀의 모든 엔트리들은 결국에는 `Utf8` 엔트리로 수렴된다
- `Class` 타입 엔트리는 클래스 이름을 참조하고 있다

**Methodref 타입**

```
#15 = Methodref          #16.#17        // java/io/PrintStream.println:(Ljava/lang/String;)V
#16 = Class              #18            // java/io/PrintStream
#17 = NameAndType        #19:#20        // println:(Ljava/lang/String;)V

#18 = Utf8               java/io/PrintStream
#19 = Utf8               println
```
- `Methodref` 타입의 #15 엔트리는 메소드를 참조를 나타낸다 
- #15는 클래스 이름인 #16을 가리키고 있다
- #15는 메소드 이름을 내포하고 있는 #17을 가리키고 있다
- #17에서 괄호 안의 값은 메서드 시그니처를 나타낸다
  - (Ljava/lang/String) 은 `String` 객체
  - V 는 `Void` 리턴

**Constant Pool 사용하기**

컴파일된 클래스 바이트 코드는 상수 풀을 심볼 테이블처럼 사용해 참조한다.

```
Code:
  stack=2, locals=2, args_size=1
     0: iconst_0
     1: istore_1
     2: iload_1
     3: bipush        10
     5: if_icmpge     22
     8: getstatic     #7                  // Field java/lang/System.out:Ljava/io/PrintStream;
    11: ldc           #13                 // String Hello from Hello.main!
    13: invokevirtual #15                 // Method java/io/PrintStream.println:(Ljava/lang/String;)V
    16: iinc          1, 1
    19: goto          2
    22: return
```
- 각 명령어는 상수 풀의 엔트리나 값을 인자로 사용한다

```
13: invokevirtual #15                 // Method java/io/PrintStream.println:(Ljava/lang/String;)V
```
- `invokevirtual` 명령어는 `println()` 메서드를 호출한다

상수 풀은 클래스에서 사용한 메서드의 이름과 시그니처만 포함하고 있다.
JVM은 메서드 탐색 과정을 개선하기 위해 메서드 테이블 자료구조를 생성한다.
- 부모 클래스를 포함한 클래스의 모든 메서드 이름과 포인터
